{"generated":"2026-06-25","sources":[{"name":"U.S. Social Security Administration","scope":"US national & state baby names","license":"Public Domain","years":"1880–2025 (states 1910–2025)"},{"name":"names-dataset (philipperemy)","scope":"Global first names by country & gender","license":"Apache-2.0; data derived from a 2019 public data leak — names only","countries":105},{"name":"mledoze/countries","scope":"Country metadata & flags","license":"ODbL"},{"name":"world-atlas / us-atlas (Natural Earth)","scope":"Map geometry","license":"Public Domain"}],"usNationalYears":[1880,2025],"usStateYears":[1910,2025],"globalCountryCount":105}